chessdotcom_export/__init__.py
chessdotcom_export/__main__.py
chessdotcom_export/common.py
chessdotcom_export/export.py
chessdotcom_export/model.py
chessdotcom_export/py.typed
chessdotcom_export-0.1.3.dist-info/LICENSE
chessdotcom_export-0.1.3.dist-info/METADATA
chessdotcom_export-0.1.3.dist-info/WHEEL
chessdotcom_export-0.1.3.dist-info/entry_points.txt
chessdotcom_export-0.1.3.dist-info/top_level.txt
chessdotcom_export-0.1.3.dist-info/RECORD
