Metadata-Version: 2.1
Name: chessdotcom-export
Version: 0.1.3
Summary: Export your chess.com games using the public API
Home-page: https://github.com/seanbreckenridge/chessdotcom_export
Author: Sean Breckenridge
Author-email: seanbrecke@gmail.com
License: MIT
Keywords: chess data
Platform: UNKNOWN
Classifier: License :: OSI Approved :: MIT License
Classifier: Programming Language :: Python
Classifier: Programming Language :: Python :: 3
Classifier: Programming Language :: Python :: 3.6
Classifier: Programming Language :: Python :: 3.7
Classifier: Programming Language :: Python :: 3.8
Classifier: Programming Language :: Python :: 3.9
Requires-Dist: click (>=7.0)
Requires-Dist: requests
Requires-Dist: IPython
Provides-Extra: testing
Requires-Dist: mypy ; extra == 'testing'
